odoo/addons/account_no_default/README.rst
odoo/addons/account_no_default/__init__.py
odoo/addons/account_no_default/__manifest__.py
odoo/addons/account_no_default/i18n/account_no_default.pot
odoo/addons/account_no_default/i18n/fr_FR.po
odoo/addons/account_no_default/i18n/it.po
odoo/addons/account_no_default/readme/CONTRIBUTORS.rst
odoo/addons/account_no_default/readme/DESCRIPTION.rst
odoo/addons/account_no_default/static/description/icon.png
odoo/addons/account_no_default/static/description/index.html
odoo/addons/account_no_default/views/account_journal_views.xml
odoo14_addon_account_no_default-14.0.1.0.1.dev7.dist-info/METADATA
odoo14_addon_account_no_default-14.0.1.0.1.dev7.dist-info/WHEEL
odoo14_addon_account_no_default-14.0.1.0.1.dev7.dist-info/top_level.txt
odoo14_addon_account_no_default-14.0.1.0.1.dev7.dist-info/RECORD
